toolforge_components_cli/__init__.py
toolforge_components_cli/cli.py
toolforge_components_cli/components.py
toolforge_components_cli/config.py
toolforge_components_cli-0.0.15.dist-info/METADATA
toolforge_components_cli-0.0.15.dist-info/WHEEL
toolforge_components_cli-0.0.15.dist-info/entry_points.txt
toolforge_components_cli-0.0.15.dist-info/licenses/LICENSE
toolforge_components_cli-0.0.15.dist-info/RECORD
